README.rst
setup.py
fast_transformers/__init__.py
fast_transformers/masking.py
fast_transformers/transformers.py
fast_transformers/utils.py
fast_transformers/weight_mapper.py
fast_transformers/aggregate/__init__.py
fast_transformers/aggregate/aggregate_cpu.cpp
fast_transformers/aggregate/aggregate_cuda.cu
fast_transformers/aggregate/clustered_aggregate_cuda.cu
fast_transformers/attention/__init__.py
fast_transformers/attention/attention_layer.py
fast_transformers/attention/causal_linear_attention.py
fast_transformers/attention/clustered_attention.py
fast_transformers/attention/conditional_full_attention.py
fast_transformers/attention/exact_topk_attention.py
fast_transformers/attention/full_attention.py
fast_transformers/attention/improved_clustered_attention.py
fast_transformers/attention/improved_clustered_causal_attention.py
fast_transformers/attention/linear_attention.py
fast_transformers/attention/local_attention.py
fast_transformers/attention/reformer_attention.py
fast_transformers/attention_registry/__init__.py
fast_transformers/attention_registry/registry.py
fast_transformers/attention_registry/spec.py
fast_transformers/builders/__init__.py
fast_transformers/builders/attention_builders.py
fast_transformers/builders/base.py
fast_transformers/builders/transformer_builders.py
fast_transformers/causal_product/__init__.py
fast_transformers/causal_product/causal_product_cpu.cpp
fast_transformers/causal_product/causal_product_cuda.cu
fast_transformers/clustering/__init__.py
fast_transformers/clustering/hamming/__init__.py
fast_transformers/clustering/hamming/cluster_cpu.cpp
fast_transformers/clustering/hamming/cluster_cuda.cu
fast_transformers/events/__init__.py
fast_transformers/events/event.py
fast_transformers/events/event_dispatcher.py
fast_transformers/events/filters.py
fast_transformers/feature_maps/__init__.py
fast_transformers/feature_maps/base.py
fast_transformers/feature_maps/fourier_features.py
fast_transformers/hashing/__init__.py
pytorch_fast_transformers.egg-info/PKG-INFO
pytorch_fast_transformers.egg-info/SOURCES.txt
pytorch_fast_transformers.egg-info/dependency_links.txt
pytorch_fast_transformers.egg-info/requires.txt
pytorch_fast_transformers.egg-info/top_level.txt
