Metadata-Version: 2.1
Name: pytorch-fast-transformers
Version: 0.4.0
Summary: Provide a library with fast transformer implementations.
Home-page: https://github.com/idiap/fast-transformers
Maintainer: Angelos Katharopoulos, Apoorv Vyas
Maintainer-email: angelos.katharopoulos@idiap.ch, avyas@idiap.ch
License: MIT
Platform: UNKNOWN
Classifier: Intended Audience :: Science/Research
Classifier: Intended Audience :: Developers
Classifier: License :: OSI Approved :: MIT License
Classifier: Topic :: Scientific/Engineering
Classifier: Programming Language :: Python
Classifier: Programming Language :: Python :: 3
Classifier: Programming Language :: Python :: 3.6
